beetl/__init__.py
beetl/__version__.py
beetl/beetl.py
beetl/comparison_result.py
beetl/result.py
beetl/compare/__init__.py
beetl/compare/compare.py
beetl/config/__init__.py
beetl/config/config_base.py
beetl/config/v1/v1_config.py
beetl/config/v1/v1_schema.py
beetl/constants/__init__.py
beetl/diff/__init__.py
beetl/diff/diff_calculator.py
beetl/diff/diff_model.py
beetl/errors/__init__.py
beetl/sources/__init__.py
beetl/sources/registrated_source.py
beetl/sources/request_threader.py
beetl/sources/csv/__init__.py
beetl/sources/csv/csv_config.py
beetl/sources/csv/csv_diff.py
beetl/sources/csv/csv_source.py
beetl/sources/excel/__init__.py
beetl/sources/excel/excel_config.py
beetl/sources/excel/excel_diff.py
beetl/sources/excel/excel_source.py
beetl/sources/excel/excel_sync.py
beetl/sources/faker/__init__.py
beetl/sources/faker/faker_config.py
beetl/sources/faker/faker_diff.py
beetl/sources/faker/faker_source.py
beetl/sources/interface/__init__.py
beetl/sources/interface/column_definition.py
beetl/sources/interface/interface_config.py
beetl/sources/interface/interface_diff.py
beetl/sources/interface/interface_source.py
beetl/sources/interface/interface_sync.py
beetl/sources/itop/__init__.py
beetl/sources/itop/itop_config.py
beetl/sources/itop/itop_source.py
beetl/sources/itop/itop_sync.py
beetl/sources/mongodb/__init__.py
beetl/sources/mongodb/mongodb_config.py
beetl/sources/mongodb/mongodb_diff.py
beetl/sources/mongodb/mongodb_source.py
beetl/sources/mongodb/mongodb_sync.py
beetl/sources/mysql/__init__.py
beetl/sources/mysql/mysql_config.py
beetl/sources/mysql/mysql_diff.py
beetl/sources/mysql/mysql_source.py
beetl/sources/mysql/mysql_sync.py
beetl/sources/postgresql/__init__.py
beetl/sources/postgresql/postgresql_config.py
beetl/sources/postgresql/postgresql_diff.py
beetl/sources/postgresql/postgresql_source.py
beetl/sources/postgresql/postgresql_sync.py
beetl/sources/rest/__init__.py
beetl/sources/rest/rest_config.py
beetl/sources/rest/rest_source.py
beetl-1.3.1.dist-info/METADATA
beetl-1.3.1.dist-info/WHEEL
beetl-1.3.1.dist-info/top_level.txt
beetl-1.3.1.dist-info/RECORD
