Metadata-Version: 2.4
Name: beetl
Version: 1.3.1
Summary: BeETL is a Python package for extracting data from one datasource, transforming it and loading it into another datasource.
Author-email: Lars Scheibling <lars.scheibling@hoglandet.se>
License: GnuPG 3.0
Project-URL: github, https://github.com/Hoglandets-IT/beetl
Keywords: python,template,package,module,cli
Classifier: Programming Language :: Python :: 3
Classifier: Operating System :: OS Independent
Requires-Python: >=3.9
Requires-Dist: requests
Requires-Dist: polars[all]>=1.14.0
Requires-Dist: sqlalchemy
Requires-Dist: pandas>=2.2.3
Requires-Dist: psycopg[binary,pool]>=3.2.3
Requires-Dist: pyyaml
Requires-Dist: pymysql
Requires-Dist: pyodbc
Requires-Dist: pymssql
Requires-Dist: mysql-connector-python
Requires-Dist: alive-progress
Requires-Dist: tabulate
Requires-Dist: pymongo>=4.10.1
Requires-Dist: cryptography
Requires-Dist: pydantic>=2.10.5
Requires-Dist: connectorx<0.4.1
Provides-Extra: xsl
Requires-Dist: lxml; extra == "xsl"
Dynamic: description
Dynamic: description-content-type
